clsa_optuna/__init__.py
clsa_optuna-0.1.0.dist-info/METADATA
clsa_optuna-0.1.0.dist-info/WHEEL
clsa_optuna-0.1.0.dist-info/top_level.txt
clsa_optuna-0.1.0.dist-info/RECORD
